[
  { "name": "Warm up",     "type": "%FTP",  "cadence": 100,  "effort":  "50%",  "duration": "6m 03s",  "color": "forest green" },

  { "name": "Max 1",    "type": "MAX",  "cadence": 100,  "effort": "MAX",  "duration": "40s",   "color": "red" },
  { "name": "Back off", "type": "%FTP", "cadence":  80,  "effort": "80%",  "duration": "20s",   "color": "dark orange" },
  { "name": "Max 2",    "type": "MAX",  "cadence": 100,  "effort": "MAX",  "duration": "40s",   "color": "red" },
  { "name": "Back off", "type": "%FTP", "cadence":  80,  "effort": "80%",  "duration": "20s",   "color": "dark orange" },
  { "name": "Max 3",    "type": "MAX",  "cadence": 100,  "effort": "MAX",  "duration": "40s",   "color": "red" },
  { "name": "Back off", "type": "%FTP", "cadence":  80,  "effort": "80%",  "duration": "20s",   "color": "dark orange" },
  { "name": "Max 4",    "type": "MAX",  "cadence": 100,  "effort": "MAX",  "duration": "40s",   "color": "red" },
  { "name": "Back off", "type": "%FTP", "cadence":  80,  "effort": "80%",  "duration": "20s",   "color": "dark orange" },
  { "name": "Max 5",    "type": "MAX",  "cadence": 100,  "effort": "MAX",  "duration": "40s",   "color": "red" },
  { "name": "Back off", "type": "%FTP", "cadence":  80,  "effort": "80%",  "duration": "20s",   "color": "dark orange" },
  { "name": "Max 6",    "type": "MAX",  "cadence": 100,  "effort": "MAX",  "duration": "40s",   "color": "red" },
  { "name": "Back off", "type": "%FTP", "cadence":  80,  "effort": "80%",  "duration": "20s",   "color": "dark orange" },
  { "name": "Max 7",    "type": "MAX",  "cadence": 100,  "effort": "MAX",  "duration": "40s",   "color": "red" },
  { "name": "Back off", "type": "%FTP", "cadence":  80,  "effort": "80%",  "duration": "20s",   "color": "dark orange" },
  { "name": "Max 8",    "type": "MAX",  "cadence": 100,  "effort": "MAX",  "duration": "40s",   "color": "red" },
  { "name": "Back off", "type": "%FTP", "cadence":  80,  "effort": "80%",  "duration": "20s",   "color": "dark orange" },

  { "name": "Recovery", "type": "%FTP", "cadence":  80,  "effort": "50%",  "duration": "3m",    "color": "yellow" },

  { "name": "Max 1",    "type": "MAX",  "cadence": 100,  "effort": "MAX",  "duration": "40s",   "color": "red" },
  { "name": "Back off", "type": "%FTP", "cadence":  80,  "effort": "80%",  "duration": "20s",   "color": "dark orange" },
  { "name": "Max 2",    "type": "MAX",  "cadence": 100,  "effort": "MAX",  "duration": "40s",   "color": "red" },
  { "name": "Back off", "type": "%FTP", "cadence":  80,  "effort": "80%",  "duration": "20s",   "color": "dark orange" },
  { "name": "Max 3",    "type": "MAX",  "cadence": 100,  "effort": "MAX",  "duration": "40s",   "color": "red" },
  { "name": "Back off", "type": "%FTP", "cadence":  80,  "effort": "80%",  "duration": "20s",   "color": "dark orange" },
  { "name": "Max 4",    "type": "MAX",  "cadence": 100,  "effort": "MAX",  "duration": "40s",   "color": "red" },
  { "name": "Back off", "type": "%FTP", "cadence":  80,  "effort": "80%",  "duration": "20s",   "color": "dark orange" },
  { "name": "Max 5",    "type": "MAX",  "cadence": 100,  "effort": "MAX",  "duration": "40s",   "color": "red" },
  { "name": "Back off", "type": "%FTP", "cadence":  80,  "effort": "80%",  "duration": "20s",   "color": "dark orange" },
  { "name": "Max 6",    "type": "MAX",  "cadence": 100,  "effort": "MAX",  "duration": "40s",   "color": "red" },
  { "name": "Back off", "type": "%FTP", "cadence":  80,  "effort": "80%",  "duration": "20s",   "color": "dark orange" },
  { "name": "Max 7",    "type": "MAX",  "cadence": 100,  "effort": "MAX",  "duration": "40s",   "color": "red" },
  { "name": "Back off", "type": "%FTP", "cadence":  80,  "effort": "80%",  "duration": "20s",   "color": "dark orange" },
  { "name": "Max 8",    "type": "MAX",  "cadence": 100,  "effort": "MAX",  "duration": "40s",   "color": "red" },
  { "name": "Back off", "type": "%FTP", "cadence":  80,  "effort": "80%",  "duration": "20s",   "color": "dark orange" },
  { "name": "Max 9",    "type": "MAX",  "cadence": 100,  "effort": "MAX",  "duration": "40s",   "color": "red" },
  { "name": "Back off", "type": "%FTP", "cadence":  80,  "effort": "80%",  "duration": "20s",   "color": "dark orange" },
  { "name": "Max 10",   "type": "MAX",  "cadence": 100,  "effort": "MAX",  "duration": "40s",   "color": "red" },
  { "name": "Back off", "type": "%FTP", "cadence":  80,  "effort": "80%",  "duration": "20s",   "color": "dark orange" },
  { "name": "Max 11",   "type": "MAX",  "cadence": 100,  "effort": "MAX",  "duration": "40s",   "color": "red" },
  { "name": "Back off", "type": "%FTP", "cadence":  80,  "effort": "80%",  "duration": "20s",   "color": "dark orange" },
  { "name": "Max 12",   "type": "MAX",  "cadence": 100,  "effort": "MAX",  "duration": "40s",   "color": "red" },
  { "name": "Back off", "type": "%FTP", "cadence":  80,  "effort": "80%",  "duration": "20s",   "color": "dark orange" },

  { "name": "Cool down", "type": "%FTP",  "cadence": 90,  "effort":  "30%",  "duration": "4m",  "color": "forest green" }
]
